nucleivuln/__init__.py
nucleivuln/conf_sample.py
nucleivuln/config.py
nucleivuln/main.py
nucleivuln/monitoring.py
nucleivuln-1.0.1.dist-info/METADATA
nucleivuln-1.0.1.dist-info/WHEEL
nucleivuln-1.0.1.dist-info/entry_points.txt
nucleivuln-1.0.1.dist-info/licenses/COPYING
nucleivuln-1.0.1.dist-info/RECORD
