Metadata-Version: 2.4
Name: NucleiVuln
Version: 1.0.1
Summary: A client designed to retrieve vulnerability-related observations from the Nuclei Git repository of templates and pushes them to a Vulnerability-Lookup instance.
License-Expression: GPL-3.0-or-later
License-File: COPYING
Keywords: Vulnerability-Lookup,Vulnerability,CVE,Nuclei
Author: Cédric Bonhomme
Author-email: cedric.bonhomme@circl.lu
Requires-Python: >=3.10,<4.0
Classifier: Development Status :: 5 - Production/Stable
Classifier: Environment :: Console
Classifier: Intended Audience :: Developers
Classifier: Intended Audience :: Science/Research
Classifier: License :: OSI Approved :: GNU General Public License v3 or later (GPLv3+)
Classifier: Operating System :: POSIX :: Linux
Classifier: Programming Language :: Python :: 3
Classifier: Programming Language :: Python :: 3.10
Classifier: Programming Language :: Python :: 3.11
Classifier: Programming Language :: Python :: 3.12
Classifier: Programming Language :: Python :: 3.13
Classifier: Programming Language :: Python :: 3.14
Classifier: Topic :: Security
Requires-Dist: pyvulnerabilitylookup (>=2.2.0)
Requires-Dist: requests (>=2.32.3)
Requires-Dist: valkey (>=6.1.0,<7.0.0)
Project-URL: Changelog, https://github.com/vulnerability-lookup/NucleiVuln/blob/main/CHANGELOG.md
Project-URL: Homepage, https://github.com/vulnerability-lookup/NucleiVuln
Project-URL: Repository, https://github.com/vulnerability-lookup/NucleiVuln
